deeplab/__init__.py
deeplab/common.py
deeplab/common_test.py
deeplab/convert_to_tflite.py
deeplab/eval.py
deeplab/export_model.py
deeplab/input_preprocess.py
deeplab/model.py
deeplab/model_test.py
deeplab/train.py
deeplab/vis.py
deeplab/core/__init__.py
deeplab/core/conv2d_ws.py
deeplab/core/conv2d_ws_test.py
deeplab/core/dense_prediction_cell.py
deeplab/core/dense_prediction_cell_test.py
deeplab/core/feature_extractor.py
deeplab/core/nas_cell.py
deeplab/core/nas_genotypes.py
deeplab/core/nas_network.py
deeplab/core/nas_network_test.py
deeplab/core/preprocess_utils.py
deeplab/core/preprocess_utils_test.py
deeplab/core/resnet_v1_beta.py
deeplab/core/resnet_v1_beta_test.py
deeplab/core/utils.py
deeplab/core/utils_test.py
deeplab/core/xception.py
deeplab/core/xception_test.py
deeplab/datasets/__init__.py
deeplab/datasets/build_ade20k_data.py
deeplab/datasets/build_cityscapes_data.py
deeplab/datasets/build_data.py
deeplab/datasets/build_voc2012_data.py
deeplab/datasets/data_generator.py
deeplab/datasets/data_generator_test.py
deeplab/datasets/remove_gt_colormap.py
deeplab/deprecated/__init__.py
deeplab/deprecated/segmentation_dataset.py
deeplab/evaluation/__init__.py
deeplab/evaluation/base_metric.py
deeplab/evaluation/eval_coco_format.py
deeplab/evaluation/eval_coco_format_test.py
deeplab/evaluation/panoptic_quality.py
deeplab/evaluation/panoptic_quality_test.py
deeplab/evaluation/parsing_covering.py
deeplab/evaluation/parsing_covering_test.py
deeplab/evaluation/streaming_metrics.py
deeplab/evaluation/streaming_metrics_test.py
deeplab/evaluation/test_utils.py
deeplab/evaluation/test_utils_test.py
deeplab/utils/__init__.py
deeplab/utils/get_dataset_colormap.py
deeplab/utils/get_dataset_colormap_test.py
deeplab/utils/save_annotation.py
deeplab/utils/train_utils.py
tfdeeplab-0.0.2.dist-info/METADATA
tfdeeplab-0.0.2.dist-info/WHEEL
tfdeeplab-0.0.2.dist-info/top_level.txt
tfdeeplab-0.0.2.dist-info/RECORD
