Metadata-Version: 2.1
Name: tfdeeplab
Version: 0.0.2
Summary: Deeplab
Author: Reza Mohebbian
Author-email: 
License: Apache License 2.0
Classifier: Programming Language :: Python :: 3.7
Classifier: Topic :: Scientific/Engineering :: Artificial Intelligence
Classifier: Intended Audience :: Developers
Classifier: Intended Audience :: Science/Research
Requires-Python: >=3.7, <3.8
Requires-Dist: tensorflow-gpu (==1.15)
